{
    "Easy": {
        "run": 100,
        "enemy": 50,
        "enemy_chance": {"rat": 50, "moth": 30, "roach": 10, "cat": 10},
        "start_multiplier": 1.0,
        "price_multiplier": 1.0,
        "day_saturation": -1,
        "orb_change": -1,
        "rest_gain": -1,
        "town_number": 5,
        "town_space": 3
    },
    "Medium": {
        "run": 70,
        "enemy": 60,
        "enemy_chance": {"rat": 30, "moth": 40, "roach": 20, "cat": 10},
        "start_multiplier": 1.1,
        "price_multiplier": 1.2,
        "day_saturation": 15,
        "orb_change": 30,
        "rest_gain": 15,
        "town_number": 4,
        "town_space": 4
    },
    "Hard": {
        "run": 50,
        "enemy": 80,
        "enemy_chance": {"rat": 10, "moth": 40, "roach": 30, "cat": 20},
        "start_multiplier": 1.2,
        "price_multiplier": 1.4,
        "day_saturation": 10,
        "orb_change": 20,
        "rest_gain": 10,
        "town_number": 3,
        "town_space": 4
    },
    "Extreme": {
        "run": 30,
        "enemy": 95,
        "enemy_chance": {"rat": 10, "moth": 20, "roach": 40, "cat": 30},
        "start_multiplier": 1.4,
        "price_multiplier": 1.6,
        "day_saturation": 8,
        "orb_change": 5,
        "rest_gain": 5,
        "town_number": 2,
        "town_space": 5
    }
}